socialprofile/__init__.py
socialprofile/admin.py
socialprofile/apps.py
socialprofile/decorators.py
socialprofile/forms.py
socialprofile/middleware.py
socialprofile/models.py
socialprofile/pipeline.py
socialprofile/serializers.py
socialprofile/signals.py
socialprofile/urls.py
socialprofile/validators.py
socialprofile/views.py
socialprofile/widgets.py
socialprofile/locale/en/LC_MESSAGES/django.mo
socialprofile/locale/en/LC_MESSAGES/django.po
socialprofile/locale/it/LC_MESSAGES/django.mo
socialprofile/locale/it/LC_MESSAGES/django.po
socialprofile/locale/it/LC_MESSAGES/djangojs.mo
socialprofile/locale/it/LC_MESSAGES/djangojs.po
socialprofile/migrations/0001_initial.py
socialprofile/migrations/0002_auto_20170107_0237.py
socialprofile/migrations/0002_models_proxy.py
socialprofile/migrations/0003_merge_20200207_1147.py
socialprofile/migrations/0004_auto_20200305_1946.py
socialprofile/migrations/0005_auto_20211030_2237.py
socialprofile/migrations/0006_auto_20211030_2242.py
socialprofile/migrations/0007_auto_20200403_1525.py
socialprofile/migrations/0008_auto_20201117_1209.py
socialprofile/migrations/0009_auto_20210214_1722.py
socialprofile/migrations/0010_auto_20211101_1214.py
socialprofile/migrations/0011_delete_group.py
socialprofile/migrations/0012_auto_20211129_1613.py
socialprofile/migrations/0013_auto_20211129_1639.py
socialprofile/migrations/0014_auto_20211129_1729.py
socialprofile/migrations/0015_auto_20211129_2117.py
socialprofile/migrations/0016_auto_20211129_2259.py
socialprofile/migrations/0017_auto_20211129_2305.py
socialprofile/migrations/0018_auto_20211130_1937.py
socialprofile/migrations/0019_auto_20211202_2216.py
socialprofile/migrations/0020_remove_socialprofile_last_accessed.py
socialprofile/migrations/0021_auto_20211214_2019.py
socialprofile/migrations/0022_auto_20211215_2357.py
socialprofile/migrations/0023_auto_20211216_1745.py
socialprofile/migrations/0024_auto_20220111_0008.py
socialprofile/migrations/0025_auto_20220317_1059.py
django_sp-1.23.3.dist-info/LICENSE
django_sp-1.23.3.dist-info/METADATA
django_sp-1.23.3.dist-info/WHEEL
django_sp-1.23.3.dist-info/top_level.txt
django_sp-1.23.3.dist-info/RECORD
