Metadata-Version: 2.1
Name: django-sp
Version: 1.23.3
Summary: Django application for custom Social Profile Auth and User model.
Home-page: https://github.com/DLRSP/django-sp
Author: DLRSP
Author-email: dlrsp.dev@gmail.com
License: MIT License
Keywords: django,socialprofile
Classifier: Development Status :: 4 - Beta
Classifier: Environment :: Web Environment
Classifier: Framework :: Django
Classifier: Framework :: Django :: 3.2
Classifier: Framework :: Django :: 4.2
Classifier: Intended Audience :: Developers
Classifier: License :: OSI Approved :: MIT License
Classifier: Operating System :: OS Independent
Classifier: Programming Language :: Python
Classifier: Programming Language :: Python :: 3
Classifier: Programming Language :: Python :: 3 :: Only
Classifier: Programming Language :: Python :: 3.8
Classifier: Programming Language :: Python :: 3.9
Classifier: Programming Language :: Python :: 3.10
Classifier: Programming Language :: Python :: 3.11
Classifier: Operating System :: OS Independent
Classifier: Topic :: Internet :: WWW/HTTP
Classifier: Topic :: Internet :: WWW/HTTP :: Dynamic Content
Classifier: Topic :: Internet :: WWW/HTTP :: WSGI :: Application
Classifier: Topic :: Software Development :: Libraries :: Application Frameworks
Classifier: Topic :: Software Development :: Libraries
Requires-Python: >=3.8
License-File: LICENSE
Requires-Dist: django-errors
Requires-Dist: python-social-auth
Requires-Dist: social-auth-app-django
Requires-Dist: django-otp
Requires-Dist: django-two-factor-auth
Requires-Dist: django-oauth-toolkit
Requires-Dist: djangorestframework
Requires-Dist: easy_thumbnails
Requires-Dist: django-cors-headers
Requires-Dist: geoip2
Requires-Dist: django-user-sessions
Requires-Dist: django-axes
Requires-Dist: phonenumbers
Requires-Dist: django-phonenumber-field
Requires-Dist: django-image-cropping
Requires-Dist: django-countries
Requires-Dist: django-crispy-forms
Requires-Dist: sweetify
Provides-Extra: testing
Requires-Dist: coverage; extra == "testing"
Requires-Dist: codecov; extra == "testing"
Provides-Extra: linting
Requires-Dist: flake8; extra == "linting"
Requires-Dist: pylint; extra == "linting"
